foolaunch/__init__.py
foolaunch/__main__.py
foolaunch-1.3.1.dist-info/METADATA
foolaunch-1.3.1.dist-info/WHEEL
foolaunch-1.3.1.dist-info/entry_points.txt
foolaunch-1.3.1.dist-info/top_level.txt
foolaunch-1.3.1.dist-info/RECORD
