Metadata-Version: 2.1
Name: foolaunch
Version: 1.3.1
Summary: A utility for launching an ec2 server from a repository of templates.
Author-email: Lynn Gabbay <gabbay@gmail.com>
License: MIT License
Project-URL: Homepage, https://github.com/ldgabbay/foolaunch
Classifier: Development Status :: 5 - Production/Stable
Classifier: Intended Audience :: Developers
Classifier: License :: OSI Approved :: MIT License
Classifier: Operating System :: OS Independent
Classifier: Programming Language :: Python :: 3
Classifier: Programming Language :: Python :: 3.6
Classifier: Programming Language :: Python :: 3.7
Classifier: Programming Language :: Python :: 3.8
Classifier: Programming Language :: Python :: 3.9
Classifier: Programming Language :: Python :: 3.10
Classifier: Programming Language :: Python :: 3.11
Classifier: Programming Language :: Python :: 3 :: Only
Classifier: Topic :: Software Development :: Libraries :: Python Modules
Requires-Python: <4,>=3.6
Requires-Dist: foostache ~=1.3
Requires-Dist: boto3 ~=1.26
